sekizai/__init__.py
sekizai/context.py
sekizai/context_processors.py
sekizai/data.py
sekizai/helpers.py
sekizai/models.py
sekizai/templatetags/__init__.py
sekizai/templatetags/sekizai_tags.py
django_sekizai-4.0.0.dist-info/LICENSE
django_sekizai-4.0.0.dist-info/METADATA
django_sekizai-4.0.0.dist-info/WHEEL
django_sekizai-4.0.0.dist-info/top_level.txt
django_sekizai-4.0.0.dist-info/RECORD
